zsh_history_to_fish/__init__.py
zsh_history_to_fish/command.py
zsh_history_to_fish-0.3.0.dist-info/LICENSE
zsh_history_to_fish-0.3.0.dist-info/METADATA
zsh_history_to_fish-0.3.0.dist-info/WHEEL
zsh_history_to_fish-0.3.0.dist-info/entry_points.txt
zsh_history_to_fish-0.3.0.dist-info/top_level.txt
zsh_history_to_fish-0.3.0.dist-info/RECORD
